{"version":1,"resource":"file:///home/will/.local/bin/selection-rofi","entries":[{"id":"CUNw","timestamp":1667525803618},{"id":"W3E0","timestamp":1667525997324},{"id":"cy9U","timestamp":1667526010620},{"id":"yymu","timestamp":1667526036167},{"id":"91Ak","timestamp":1667526954051},{"id":"kR1E","timestamp":1667527138738},{"id":"IWy4","source":"undoRedo.source","timestamp":1667527187660},{"id":"kAUj","timestamp":1667527188577},{"id":"rKiH","timestamp":1667527898222},{"id":"m944","source":"undoRedo.source","timestamp":1667527929450},{"id":"crBZ","timestamp":1667527960384},{"id":"qYRQ","timestamp":1667528277117}]}